XStatic_Bootbox-5.5.1.1-py3.13-nspkg.pth
xstatic/pkg/bootbox/__init__.py
xstatic/pkg/bootbox/data/bootbox.all.min.js
xstatic/pkg/bootbox/data/bootbox.locales.min.js
xstatic/pkg/bootbox/data/bootbox.min.js
xstatic_bootbox-5.5.1.1.dist-info/METADATA
xstatic_bootbox-5.5.1.1.dist-info/WHEEL
xstatic_bootbox-5.5.1.1.dist-info/namespace_packages.txt
xstatic_bootbox-5.5.1.1.dist-info/top_level.txt
xstatic_bootbox-5.5.1.1.dist-info/RECORD
