Metadata-Version: 2.4
Name: XStatic-Bootbox
Version: 5.5.1.1
Summary: Bootbox 5.5.1 (XStatic packaging standard)
Home-page: http://bootboxjs.com/
Maintainer: Thomas Waldmann
Maintainer-email: tw@waldmann-edv.de
License: (same as Bootbox)
Keywords: bootbox xstatic
Platform: any
Dynamic: description
Dynamic: home-page
Dynamic: keywords
Dynamic: license
Dynamic: maintainer
Dynamic: maintainer-email
Dynamic: platform
Dynamic: summary
